hooks/__init__.py
hooks/kubernetes_secret.py
hooks/rule.py
hooks/validate.py
pre_commit_k8s-0.0.3.dist-info/LICENCE
pre_commit_k8s-0.0.3.dist-info/METADATA
pre_commit_k8s-0.0.3.dist-info/WHEEL
pre_commit_k8s-0.0.3.dist-info/entry_points.txt
pre_commit_k8s-0.0.3.dist-info/top_level.txt
pre_commit_k8s-0.0.3.dist-info/RECORD
