Metadata-Version: 2.1
Name: pre-commit-k8s
Version: 0.0.3
Summary: pre-commit rules for Kubernetes related files
Home-page: https://github.com/zwennesm/pre-commit-k8s
Author: Martijn Zwennes
Author-email: martijnzwennes@pm.me
License: UNKNOWN
Platform: UNKNOWN
Classifier: Programming Language :: Python :: 3
Classifier: License :: OSI Approved :: MIT License
Classifier: Operating System :: OS Independent
Requires-Python: >=3.6
